<package>
	<id>com.jianfengzhi.appsyncunified</id>
	<name>AppSync Unified</name>
	<version>32.0</version>
	<compatibility>
		<firmware>
			<miniOS>5.0</miniOS>
			<maxiOS>12.1.2</maxiOS>
		</firmware>
	</compatibility>
	<shortDescription>允许设备安装未签名的应用</shortDescription>
	<descriptionlist>
		<description>绕过系统签名校验，允许设备安装未签名的APP。</description>
	</descriptionlist>
	<links>
		<link>
			<name> 开发者主页</name>
			<url>https://cydia.angelxwind.net</url>
			<iconclass>fa fa-code</iconclass>
		</link>
	</links>
</package>